extended_sql/__init__.py
extended_sql/async_manager.py
extended_sql/models.py
extended_sql/utils.py
extended_sql-0.1.0.dist-info/METADATA
extended_sql-0.1.0.dist-info/WHEEL
extended_sql-0.1.0.dist-info/RECORD
